rasa_extractors/__init__.py
rasa_extractors/flash_text.py
rasa_extractors-0.1.2.dist-info/COPYING
rasa_extractors-0.1.2.dist-info/WHEEL
rasa_extractors-0.1.2.dist-info/METADATA
rasa_extractors-0.1.2.dist-info/RECORD
